formualizer-0.3.1.dist-info/METADATA
formualizer-0.3.1.dist-info/WHEEL
formualizer/__init__.py
formualizer/visitor.py
formualizer/py.typed
formualizer/_types.py
formualizer/formualizer_py.cpython-312-x86_64-linux-gnu.so
formualizer-0.3.1.dist-info/RECORD
