Metadata-Version: 2.4
Name: formualizer
Version: 0.3.1
Classifier: Programming Language :: Rust
Classifier: Programming Language :: Python :: Implementation :: CPython
Classifier: Programming Language :: Python :: Implementation :: PyPy
Requires-Dist: pytest>=7.0 ; extra == 'dev'
Requires-Dist: pytest-cov>=4.0 ; extra == 'dev'
Requires-Dist: ruff>=0.1.0 ; extra == 'dev'
Requires-Dist: mypy>=1.0 ; extra == 'dev'
Requires-Dist: openpyxl ; extra == 'dev'
Provides-Extra: dev
Summary: Fast Excel-formula tooling (Python bindings)
License: MIT
Requires-Python: >=3.8
